trame/__init__.py
trame/modules/__init__.py
trame/modules/tweakpane.py
trame/widgets/__init__.py
trame/widgets/tweakpane.py
trame_tweakpane/__init__.py
trame_tweakpane/module/__init__.py
trame_tweakpane/module/serve/trame_tweakpane.umd.js
trame_tweakpane/widgets/__init__.py
trame_tweakpane/widgets/tweakpane.py
trame_tweakpane-0.1.3.dist-info/METADATA
trame_tweakpane-0.1.3.dist-info/WHEEL
trame_tweakpane-0.1.3.dist-info/entry_points.txt
trame_tweakpane-0.1.3.dist-info/licenses/LICENSE
trame_tweakpane-0.1.3.dist-info/RECORD
