Metadata-Version: 2.3
Name: trame-tweakpane
Version: 0.1.3
Summary: TweakPane widgets for trame
Author-email: Sebastien Jourdain <sebastien.jourdain@kitware.com>
Maintainer-email: Sebastien Jourdain <sebastien.jourdain@kitware.com>
License: MIT License
License-File: LICENSE
Keywords: components,trame,tweakpane,web
Classifier: Development Status :: 4 - Beta
Classifier: Intended Audience :: Developers
Classifier: License :: OSI Approved :: Apache Software License
Classifier: Programming Language :: Python :: 3
Classifier: Programming Language :: Python :: 3.7
Requires-Python: >=3.7
Requires-Dist: trame-client
Provides-Extra: ci
Requires-Dist: build; extra == 'ci'
Requires-Dist: pre-commit; extra == 'ci'
Provides-Extra: dev
Requires-Dist: pre-commit; extra == 'dev'
Requires-Dist: python-semantic-release; extra == 'dev'
Requires-Dist: ruff; extra == 'dev'
